Metadata-Version: 2.1
Name: jfricas
Version: 2.0.0
Summary: FriCAS Jupyter Kernel.
Home-page: http://github.com/fricas/jfricas
Author: Kurt Pagani, Ralf Hemmecke
Author-email: jfricas@hemmecke.org
License: BSD
Keywords: fricas,jupyter,computer_algebra
Classifier: Development Status :: 4 - Beta
Classifier: License :: OSI Approved :: BSD License
Classifier: Programming Language :: Python :: 3.5
Classifier: Operating System :: POSIX :: Linux
Classifier: Topic :: Scientific/Engineering :: Mathematics
Requires-Python: >=3.5
License-File: LICENSE
